<?xml version="1.0" encoding="UTF-8"?>
<UnityGameFramework>
  <ResourceBuilder>
    <Settings>
      <InternalResourceVersion>19</InternalResourceVersion>
      <Platforms>1</Platforms>
      <AssetBundleCompression>0</AssetBundleCompression>
      <CompressionHelperTypeName>UnityGameFramework.Runtime.DefaultCompressionHelper</CompressionHelperTypeName>
      <AdditionalCompressionSelected>True</AdditionalCompressionSelected>
      <ForceRebuildAssetBundleSelected>True</ForceRebuildAssetBundleSelected>
      <BuildEventHandlerTypeName>Game.Editor.GameBuildEventHandler</BuildEventHandlerTypeName>
      <OutputDirectory>E:/UnityProjs/StarForce_HybridCLR/ABs</OutputDirectory>
      <OutputPackageSelected>True</OutputPackageSelected>
      <OutputFullSelected>True</OutputFullSelected>
      <OutputPackedSelected>True</OutputPackedSelected>
    </Settings>
  </ResourceBuilder>
</UnityGameFramework>